{
  "project": "AFIP",
  "current_milestone": "Production Milestone B",
  "latest_milestone": "Production Milestone B",
  "latest_commit_base": "5f639ae",
  "latest_pack": 18,
  "latest_pack_name": "Performance Attribution Layer",
  "next_pack": "Production Milestone B Pack 19",
  "status": "Pack 18 complete in incremental package",
  "tests": "342 passed",
  "test_count_expected": 342,
  "quality_check": "PASS",
  "quality_status": "PASS",
  "financial_naming": "PASS",
  "financial_naming_status": "PASS"
}
